{
	"$schema": "http://schema.management.azure.com/schemas/2015-01-01/deploymentTemplate.json#",
	"contentVersion": "1.0.0.0",
	"parameters": {
		"factoryName": {
			"type": "string",
			"metadata": "Data Factory name",
			"defaultValue": "formula1dl114"
		}
	},
	"variables": {
		"factoryId": "[concat('Microsoft.DataFactory/factories/', parameters('factoryName'))]"
	},
	"resources": [
		{
			"name": "[concat(parameters('factoryName'), '/ds_source_data')]",
			"type": "Microsoft.DataFactory/factories/datasets",
			"apiVersion": "2018-06-01",
			"properties": {
				"linkedServiceName": {
					"referenceName": "ls_adls_gen2",
					"type": "LinkedServiceReference"
				},
				"annotations": [],
				"type": "DelimitedText",
				"typeProperties": {
					"location": {
						"type": "AzureBlobFSLocation",
						"fileName": "template.txt",
						"fileSystem": "test"
					},
					"columnDelimiter": ",",
					"escapeChar": "\\",
					"firstRowAsHeader": false,
					"quoteChar": "\""
				},
				"schema": [
					{
						"type": "String"
					}
				]
			},
			"dependsOn": []
		},
		{
			"name": "[concat(parameters('factoryName'), '/ds_url_web')]",
			"type": "Microsoft.DataFactory/factories/datasets",
			"apiVersion": "2018-06-01",
			"properties": {
				"linkedServiceName": {
					"referenceName": "AzureDataLakeStorage1",
					"type": "LinkedServiceReference"
				},
				"parameters": {
					"file_name": {
						"type": "String",
						"defaultValue": "seasons"
					}
				},
				"annotations": [],
				"type": "DelimitedText",
				"typeProperties": {
					"location": {
						"type": "AzureBlobFSLocation",
						"fileName": {
							"value": "@dataset().file_name",
							"type": "Expression"
						},
						"folderPath": "seasons",
						"fileSystem": "output"
					},
					"columnDelimiter": ",",
					"escapeChar": "",
					"firstRowAsHeader": false,
					"quoteChar": ""
				},
				"schema": []
			},
			"dependsOn": []
		},
		{
			"name": "[concat(parameters('factoryName'), '/ds_web_source_year')]",
			"type": "Microsoft.DataFactory/factories/datasets",
			"apiVersion": "2018-06-01",
			"properties": {
				"linkedServiceName": {
					"referenceName": "AzureDataLakeStorage1",
					"type": "LinkedServiceReference"
				},
				"annotations": [],
				"type": "DelimitedText",
				"typeProperties": {
					"location": {
						"type": "AzureBlobFSLocation",
						"fileName": "a.txt",
						"fileSystem": "input"
					},
					"columnDelimiter": ",",
					"escapeChar": "",
					"firstRowAsHeader": false,
					"quoteChar": ""
				},
				"schema": [
					{
						"name": "Gu",
						"type": "String"
					}
				]
			},
			"dependsOn": []
		},
		{
			"name": "[concat(parameters('factoryName'), '/ds_year_parents')]",
			"type": "Microsoft.DataFactory/factories/datasets",
			"apiVersion": "2018-06-01",
			"properties": {
				"linkedServiceName": {
					"referenceName": "AzureDataLakeStorage1",
					"type": "LinkedServiceReference"
				},
				"annotations": [],
				"type": "DelimitedText",
				"typeProperties": {
					"location": {
						"type": "AzureBlobFSLocation",
						"fileName": {
							"value": "@concat('season',item().season,'.json')",
							"type": "Expression"
						},
						"folderPath": {
							"value": "@concat('Races','/',string(utcNow('yyyyMMdd')))",
							"type": "Expression"
						},
						"fileSystem": "output"
					},
					"columnDelimiter": ",",
					"escapeChar": "",
					"firstRowAsHeader": false,
					"quoteChar": ""
				},
				"schema": []
			},
			"dependsOn": []
		},
		{
			"name": "[concat(parameters('factoryName'), '/pract_foreach')]",
			"type": "Microsoft.DataFactory/factories/datasets",
			"apiVersion": "2018-06-01",
			"properties": {
				"linkedServiceName": {
					"referenceName": "AzureDataLakeStorage1",
					"type": "LinkedServiceReference"
				},
				"parameters": {
					"foldername": {
						"type": "string"
					}
				},
				"annotations": [],
				"type": "Binary",
				"typeProperties": {
					"location": {
						"type": "AzureBlobFSLocation",
						"fileName": {
							"value": "@dataset().foldername",
							"type": "Expression"
						},
						"folderPath": "practforeach",
						"fileSystem": "raw"
					}
				}
			},
			"dependsOn": []
		},
		{
			"name": "[concat(parameters('factoryName'), '/PL_INGEST_DRIVERS_DATA')]",
			"type": "Microsoft.DataFactory/factories/pipelines",
			"apiVersion": "2018-06-01",
			"properties": {
				"activities": [
					{
						"name": "act_Web1",
						"description": "This activity will get Drivers data from API",
						"type": "WebActivity",
						"dependsOn": [],
						"policy": {
							"timeout": "0.12:00:00",
							"retry": 0,
							"retryIntervalInSeconds": 30,
							"secureOutput": false,
							"secureInput": false
						},
						"userProperties": [],
						"typeProperties": {
							"method": "GET",
							"headers": {},
							"url": "http://ergast.com/api/f1/drivers.json"
						}
					},
					{
						"name": "act_Set _limit_variable1",
						"type": "SetVariable",
						"dependsOn": [
							{
								"activity": "act_Web1",
								"dependencyConditions": [
									"Succeeded"
								]
							}
						],
						"policy": {
							"secureOutput": false,
							"secureInput": false
						},
						"userProperties": [],
						"typeProperties": {
							"variableName": "drivers_limit",
							"value": {
								"value": "@activity('act_Web1').output.MRData.total",
								"type": "Expression"
							}
						}
					},
					{
						"name": "act_Web2",
						"type": "WebActivity",
						"dependsOn": [
							{
								"activity": "act_Set _limit_variable1",
								"dependencyConditions": [
									"Succeeded"
								]
							}
						],
						"policy": {
							"timeout": "0.12:00:00",
							"retry": 0,
							"retryIntervalInSeconds": 30,
							"secureOutput": false,
							"secureInput": false
						},
						"userProperties": [],
						"typeProperties": {
							"method": "GET",
							"headers": {},
							"url": {
								"value": "@concat('http://ergast.com/api/f1/drivers.json?limit=',variables('drivers_limit'))",
								"type": "Expression"
							}
						}
					},
					{
						"name": "act_Set_Drivers_data_variable",
						"type": "SetVariable",
						"dependsOn": [
							{
								"activity": "act_Web2",
								"dependencyConditions": [
									"Succeeded"
								]
							}
						],
						"policy": {
							"secureOutput": false,
							"secureInput": false
						},
						"userProperties": [],
						"typeProperties": {
							"variableName": "drivers_data",
							"value": {
								"value": "@{activity('act_Web2').output.MRData.DriverTable.Drivers}",
								"type": "Expression"
							}
						}
					},
					{
						"name": "act_Copy_drivers_data_to_bronze",
						"type": "Copy",
						"dependsOn": [
							{
								"activity": "act_Set_Drivers_data_variable",
								"dependencyConditions": [
									"Succeeded"
								]
							}
						],
						"policy": {
							"timeout": "0.12:00:00",
							"retry": 0,
							"retryIntervalInSeconds": 30,
							"secureOutput": false,
							"secureInput": false
						},
						"userProperties": [],
						"typeProperties": {
							"source": {
								"type": "DelimitedTextSource",
								"additionalColumns": [
									{
										"name": "my_column",
										"value": {
											"value": "@variables('drivers_data')",
											"type": "Expression"
										}
									}
								],
								"storeSettings": {
									"type": "AzureBlobFSReadSettings",
									"recursive": true,
									"enablePartitionDiscovery": false
								},
								"formatSettings": {
									"type": "DelimitedTextReadSettings"
								}
							},
							"sink": {
								"type": "DelimitedTextSink",
								"storeSettings": {
									"type": "AzureBlobFSWriteSettings"
								},
								"formatSettings": {
									"type": "DelimitedTextWriteSettings",
									"quoteAllText": true,
									"fileExtension": ".txt"
								}
							},
							"enableStaging": false,
							"translator": {
								"type": "TabularTranslator",
								"mappings": [
									{
										"source": {
											"name": "my_column",
											"type": "String"
										},
										"sink": {
											"type": "String",
											"physicalType": "String",
											"ordinal": 1
										}
									}
								],
								"typeConversion": true,
								"typeConversionSettings": {
									"allowDataTruncation": true,
									"treatBooleanAsNumber": false
								}
							}
						},
						"inputs": [
							{
								"referenceName": "DS_SOURCE_TEMP_TXT_DATA4",
								"type": "DatasetReference",
								"parameters": {}
							}
						],
						"outputs": [
							{
								"referenceName": "DS_SINK_DRIVERS_DATA2",
								"type": "DatasetReference",
								"parameters": {}
							}
						]
					}
				],
				"policy": {
					"elapsedTimeMetric": {}
				},
				"variables": {
					"drivers_limit": {
						"type": "String"
					},
					"drivers_data": {
						"type": "String"
					}
				},
				"folder": {
					"name": "API_Ingestion_Pipelines"
				},
				"annotations": []
			},
			"dependsOn": []
		},
		{
			"name": "[concat(parameters('factoryName'), '/PL_INGEST_RESULTS_DATA')]",
			"type": "Microsoft.DataFactory/factories/pipelines",
			"apiVersion": "2018-06-01",
			"properties": {
				"activities": [
					{
						"name": "act_Web1",
						"description": "This activity will get races data from API to iterate season and round wise to get Results data",
						"type": "WebActivity",
						"dependsOn": [],
						"policy": {
							"timeout": "0.12:00:00",
							"retry": 0,
							"retryIntervalInSeconds": 30,
							"secureOutput": false,
							"secureInput": false
						},
						"userProperties": [],
						"typeProperties": {
							"method": "GET",
							"headers": {},
							"url": {
								"value": "@concat('http://ergast.com/api/f1/',pipeline().parameters.year_from_races_pl,'.json')",
								"type": "Expression"
							}
						}
					},
					{
						"name": "act_ForEach_roundwise_iteration",
						"description": "This activity will iterate through each round of particular season",
						"type": "ForEach",
						"dependsOn": [
							{
								"activity": "act_Web1",
								"dependencyConditions": [
									"Succeeded"
								]
							}
						],
						"userProperties": [],
						"typeProperties": {
							"items": {
								"value": "@activity('act_Web1').output.MRData.RaceTable.Races",
								"type": "Expression"
							},
							"isSequential": true,
							"activities": [
								{
									"name": "act_Web2",
									"description": "This activity will get data from races results API",
									"type": "WebActivity",
									"dependsOn": [],
									"policy": {
										"timeout": "0.12:00:00",
										"retry": 0,
										"retryIntervalInSeconds": 30,
										"secureOutput": false,
										"secureInput": false
									},
									"userProperties": [],
									"typeProperties": {
										"method": "GET",
										"headers": {},
										"url": {
											"value": "@concat('http://ergast.com/api/f1/',pipeline().parameters.year_from_races_pl,'/',item().round,'/results.json')",
											"type": "Expression"
										}
									}
								},
								{
									"name": "act_Set_Races_Results_data_variable",
									"description": "This activity will save races Results data into races_results_data variable which is taken from API",
									"type": "SetVariable",
									"dependsOn": [
										{
											"activity": "act_Web2",
											"dependencyConditions": [
												"Succeeded"
											]
										}
									],
									"policy": {
										"secureOutput": false,
										"secureInput": false
									},
									"userProperties": [],
									"typeProperties": {
										"variableName": "race_results_data",
										"value": {
											"value": "@{activity('act_Web2').output.MRData.RaceTable.Races}",
											"type": "Expression"
										}
									}
								},
								{
									"name": "act_Copy_races_results_data",
									"description": "This activity will copy races results data to bronze container in JSON file format",
									"type": "Copy",
									"dependsOn": [
										{
											"activity": "act_Set_Races_Results_data_variable",
											"dependencyConditions": [
												"Succeeded"
											]
										}
									],
									"policy": {
										"timeout": "0.12:00:00",
										"retry": 0,
										"retryIntervalInSeconds": 30,
										"secureOutput": false,
										"secureInput": false
									},
									"userProperties": [],
									"typeProperties": {
										"source": {
											"type": "DelimitedTextSource",
											"additionalColumns": [
												{
													"name": "my_column",
													"value": {
														"value": "@variables('race_results_data')",
														"type": "Expression"
													}
												}
											],
											"storeSettings": {
												"type": "AzureBlobFSReadSettings",
												"recursive": true,
												"enablePartitionDiscovery": false
											},
											"formatSettings": {
												"type": "DelimitedTextReadSettings"
											}
										},
										"sink": {
											"type": "DelimitedTextSink",
											"storeSettings": {
												"type": "AzureBlobFSWriteSettings"
											},
											"formatSettings": {
												"type": "DelimitedTextWriteSettings",
												"quoteAllText": true,
												"fileExtension": ".txt"
											}
										},
										"enableStaging": false,
										"translator": {
											"type": "TabularTranslator",
											"mappings": [
												{
													"source": {
														"name": "my_column",
														"type": "String"
													},
													"sink": {
														"type": "String",
														"physicalType": "String",
														"ordinal": 1
													}
												}
											],
											"typeConversion": true,
											"typeConversionSettings": {
												"allowDataTruncation": true,
												"treatBooleanAsNumber": false
											}
										}
									},
									"inputs": [
										{
											"referenceName": "DS_SOURCE_TEMP_TXT_DATA5",
											"type": "DatasetReference",
											"parameters": {}
										}
									],
									"outputs": [
										{
											"referenceName": "DS_SINK_RACES_RESULTS_DATA2",
											"type": "DatasetReference",
											"parameters": {
												"season": {
													"value": "@pipeline().parameters.year_from_races_pl",
													"type": "Expression"
												},
												"Round": {
													"value": "@item().round",
													"type": "Expression"
												}
											}
										}
									]
								}
							]
						}
					}
				],
				"policy": {
					"elapsedTimeMetric": {}
				},
				"parameters": {
					"year_from_races_pl": {
						"type": "string"
					}
				},
				"variables": {
					"race_results_data": {
						"type": "String"
					}
				},
				"folder": {
					"name": "API_Ingestion_Pipelines"
				},
				"annotations": []
			},
			"dependsOn": []
		},
		{
			"name": "[concat(parameters('factoryName'), '/PL_INGEST_SEASON_DATA')]",
			"type": "Microsoft.DataFactory/factories/pipelines",
			"apiVersion": "2018-06-01",
			"properties": {
				"description": "This pipeline will ingest season data from ergast API in JSON file format",
				"activities": [
					{
						"name": "act_web1",
						"description": "This activity will get data from API",
						"type": "WebActivity",
						"dependsOn": [],
						"policy": {
							"timeout": "0.12:00:00",
							"retry": 0,
							"retryIntervalInSeconds": 30,
							"secureOutput": false,
							"secureInput": false
						},
						"userProperties": [],
						"typeProperties": {
							"method": "GET",
							"headers": {},
							"url": "http://ergast.com/api/f1/seasons.json"
						}
					},
					{
						"name": "act_set_limit_variable_value",
						"type": "SetVariable",
						"dependsOn": [
							{
								"activity": "act_web1",
								"dependencyConditions": [
									"Succeeded"
								]
							}
						],
						"policy": {
							"secureOutput": false,
							"secureInput": false
						},
						"userProperties": [],
						"typeProperties": {
							"variableName": "Limit",
							"value": {
								"value": "@activity('act_web1').output.MRData.total",
								"type": "Expression"
							}
						}
					},
					{
						"name": "act_Web2",
						"type": "WebActivity",
						"dependsOn": [
							{
								"activity": "act_set_limit_variable_value",
								"dependencyConditions": [
									"Succeeded"
								]
							}
						],
						"policy": {
							"timeout": "0.12:00:00",
							"retry": 0,
							"retryIntervalInSeconds": 30,
							"secureOutput": false,
							"secureInput": false
						},
						"userProperties": [],
						"typeProperties": {
							"method": "GET",
							"headers": {},
							"url": {
								"value": "@concat('http://ergast.com/api/f1/seasons.json?limit=',variables('Limit'))",
								"type": "Expression"
							}
						}
					},
					{
						"name": "act_Set_variable_seasons_data",
						"type": "SetVariable",
						"dependsOn": [
							{
								"activity": "act_Web2",
								"dependencyConditions": [
									"Succeeded"
								]
							}
						],
						"policy": {
							"secureOutput": false,
							"secureInput": false
						},
						"userProperties": [],
						"typeProperties": {
							"variableName": "seasons_data",
							"value": {
								"value": "@{activity('act_Web2').output.MRData.SeasonTable.Seasons}",
								"type": "Expression"
							}
						}
					},
					{
						"name": "act_Copy_seasons_data_to_bronze_layer",
						"type": "Copy",
						"dependsOn": [
							{
								"activity": "act_Set_variable_seasons_data",
								"dependencyConditions": [
									"Succeeded"
								]
							}
						],
						"policy": {
							"timeout": "0.12:00:00",
							"retry": 0,
							"retryIntervalInSeconds": 30,
							"secureOutput": false,
							"secureInput": false
						},
						"userProperties": [],
						"typeProperties": {
							"source": {
								"type": "DelimitedTextSource",
								"additionalColumns": [
									{
										"name": "my_column",
										"value": {
											"value": "@variables('seasons_data')",
											"type": "Expression"
										}
									}
								],
								"storeSettings": {
									"type": "AzureBlobFSReadSettings",
									"recursive": true,
									"enablePartitionDiscovery": false
								},
								"formatSettings": {
									"type": "DelimitedTextReadSettings"
								}
							},
							"sink": {
								"type": "DelimitedTextSink",
								"storeSettings": {
									"type": "AzureBlobFSWriteSettings"
								},
								"formatSettings": {
									"type": "DelimitedTextWriteSettings",
									"quoteAllText": true,
									"fileExtension": ".txt"
								}
							},
							"enableStaging": false,
							"translator": {
								"type": "TabularTranslator",
								"mappings": [
									{
										"source": {
											"name": "my_column",
											"type": "String"
										},
										"sink": {
											"type": "String",
											"physicalType": "String",
											"ordinal": 1
										}
									}
								],
								"typeConversion": true,
								"typeConversionSettings": {
									"allowDataTruncation": true,
									"treatBooleanAsNumber": false
								}
							}
						},
						"inputs": [
							{
								"referenceName": "DS_SOURCE_TEMP_TXT_DATA6",
								"type": "DatasetReference",
								"parameters": {}
							}
						],
						"outputs": [
							{
								"referenceName": "DS_SINK_SEASONS_DATA1",
								"type": "DatasetReference",
								"parameters": {}
							}
						]
					}
				],
				"policy": {
					"elapsedTimeMetric": {}
				},
				"variables": {
					"Limit": {
						"type": "String"
					},
					"seasons_data": {
						"type": "String"
					}
				},
				"folder": {
					"name": "API_Ingestion_Pipelines"
				},
				"annotations": []
			},
			"dependsOn": []
		},
		{
			"name": "[concat(parameters('factoryName'), '/pl_ingestion')]",
			"type": "Microsoft.DataFactory/factories/pipelines",
			"apiVersion": "2018-06-01",
			"properties": {
				"activities": [
					{
						"name": "actCopy_data_for_season",
						"type": "Copy",
						"dependsOn": [],
						"policy": {
							"timeout": "0.12:00:00",
							"retry": 0,
							"retryIntervalInSeconds": 30,
							"secureOutput": false,
							"secureInput": false
						},
						"userProperties": [],
						"typeProperties": {
							"source": {
								"type": "JsonSource",
								"storeSettings": {
									"type": "HttpReadSettings",
									"requestMethod": "GET"
								},
								"formatSettings": {
									"type": "JsonReadSettings"
								}
							},
							"sink": {
								"type": "JsonSink",
								"storeSettings": {
									"type": "AzureBlobFSWriteSettings"
								},
								"formatSettings": {
									"type": "JsonWriteSettings"
								}
							},
							"enableStaging": false
						},
						"inputs": [
							{
								"referenceName": "ds_http_server",
								"type": "DatasetReference",
								"parameters": {
									"relative_url": "seasons.json?limit=100"
								}
							}
						],
						"outputs": [
							{
								"referenceName": "ds_adls_storage",
								"type": "DatasetReference",
								"parameters": {
									"directory_path": {
										"value": "@concat('bronze/seasons/',string(utcnow('yyyyMMdd')))",
										"type": "Expression"
									},
									"filename": "season.json"
								}
							}
						]
					},
					{
						"name": "act_Lookup_season",
						"type": "Lookup",
						"dependsOn": [
							{
								"activity": "actCopy_data_for_season",
								"dependencyConditions": [
									"Succeeded"
								]
							}
						],
						"policy": {
							"timeout": "0.12:00:00",
							"retry": 0,
							"retryIntervalInSeconds": 30,
							"secureOutput": false,
							"secureInput": false
						},
						"userProperties": [],
						"typeProperties": {
							"source": {
								"type": "JsonSource",
								"storeSettings": {
									"type": "AzureBlobFSReadSettings",
									"recursive": true,
									"wildcardFileName": "*.json",
									"enablePartitionDiscovery": false
								},
								"formatSettings": {
									"type": "JsonReadSettings"
								}
							},
							"dataset": {
								"referenceName": "ds_adls_storage_without_parameter",
								"type": "DatasetReference",
								"parameters": {
									"directory_path": {
										"value": "@concat('bronze/seasons/',string(utcnow('yyyyMMdd')))",
										"type": "Expression"
									}
								}
							},
							"firstRowOnly": false
						}
					},
					{
						"name": "ForEach_races",
						"type": "ForEach",
						"dependsOn": [
							{
								"activity": "act_Lookup_season",
								"dependencyConditions": [
									"Succeeded"
								]
							}
						],
						"userProperties": [],
						"typeProperties": {
							"items": {
								"value": "@activity('act_Lookup_season').output.value[0].MRData.SeasonTable.Seasons",
								"type": "Expression"
							},
							"batchCount": 20,
							"activities": [
								{
									"name": "act_Copy_data_races",
									"type": "Copy",
									"dependsOn": [],
									"policy": {
										"timeout": "0.12:00:00",
										"retry": 0,
										"retryIntervalInSeconds": 30,
										"secureOutput": false,
										"secureInput": false
									},
									"userProperties": [],
									"typeProperties": {
										"source": {
											"type": "JsonSource",
											"storeSettings": {
												"type": "HttpReadSettings",
												"requestMethod": "GET"
											},
											"formatSettings": {
												"type": "JsonReadSettings"
											}
										},
										"sink": {
											"type": "JsonSink",
											"storeSettings": {
												"type": "AzureBlobFSWriteSettings"
											},
											"formatSettings": {
												"type": "JsonWriteSettings"
											}
										},
										"enableStaging": false
									},
									"inputs": [
										{
											"referenceName": "ds_http_server",
											"type": "DatasetReference",
											"parameters": {
												"relative_url": {
													"value": "@concat(item()['season'],'.json?=100')",
													"type": "Expression"
												}
											}
										}
									],
									"outputs": [
										{
											"referenceName": "ds_adls_storage",
											"type": "DatasetReference",
											"parameters": {
												"directory_path": {
													"value": "@concat('bronze/races/',string(utcnow('yyyyMMdd')))",
													"type": "Expression"
												},
												"filename": {
													"value": "@concat(item()['season'],'.json')",
													"type": "Expression"
												}
											}
										}
									]
								}
							]
						}
					},
					{
						"name": "Lookup_races",
						"type": "Lookup",
						"dependsOn": [
							{
								"activity": "ForEach_races",
								"dependencyConditions": [
									"Succeeded"
								]
							}
						],
						"policy": {
							"timeout": "0.12:00:00",
							"retry": 0,
							"retryIntervalInSeconds": 30,
							"secureOutput": false,
							"secureInput": false
						},
						"userProperties": [],
						"typeProperties": {
							"source": {
								"type": "JsonSource",
								"storeSettings": {
									"type": "AzureBlobFSReadSettings",
									"recursive": true,
									"wildcardFileName": "*.json",
									"enablePartitionDiscovery": false
								},
								"formatSettings": {
									"type": "JsonReadSettings"
								}
							},
							"dataset": {
								"referenceName": "ds_adls_storage_without_parameter",
								"type": "DatasetReference",
								"parameters": {
									"directory_path": {
										"value": "@concat('bronze/races/',string(utcnow('yyyyMMdd')))",
										"type": "Expression"
									}
								}
							},
							"firstRowOnly": false
						}
					},
					{
						"name": "_act_ForEach_result",
						"type": "ForEach",
						"dependsOn": [
							{
								"activity": "Lookup_races",
								"dependencyConditions": [
									"Succeeded"
								]
							}
						],
						"userProperties": [],
						"typeProperties": {
							"items": {
								"value": "@activity('Lookup_races').output.value",
								"type": "Expression"
							},
							"isSequential": true,
							"activities": [
								{
									"name": "Execute Pipeline1",
									"type": "ExecutePipeline",
									"dependsOn": [
										{
											"activity": "Set variable1",
											"dependencyConditions": [
												"Succeeded"
											]
										}
									],
									"policy": {
										"secureInput": false
									},
									"userProperties": [],
									"typeProperties": {
										"waitOnCompletion": true,
										"parameters": {}
									}
								},
								{
									"name": "Set variable1",
									"type": "SetVariable",
									"dependsOn": [],
									"policy": {
										"secureOutput": false,
										"secureInput": false
									},
									"userProperties": [],
									"typeProperties": {
										"variableName": "season_round",
										"value": {
											"value": "@item().MRData.RaceTable.Races",
											"type": "Expression"
										}
									}
								}
							]
						}
					}
				],
				"policy": {
					"elapsedTimeMetric": {}
				},
				"variables": {
					"round_id": {
						"type": "String"
					},
					"season_round": {
						"type": "String"
					},
					"season_id": {
						"type": "String"
					}
				},
				"folder": {
					"name": "ingestion"
				},
				"annotations": [],
				"lastPublishTime": "2024-04-12T18:05:40Z"
			},
			"dependsOn": []
		},
		{
			"name": "[concat(parameters('factoryName'), '/pl_ingestion_driver')]",
			"type": "Microsoft.DataFactory/factories/pipelines",
			"apiVersion": "2018-06-01",
			"properties": {
				"activities": [
					{
						"name": "Copy data_driver",
						"type": "Copy",
						"dependsOn": [],
						"policy": {
							"timeout": "0.12:00:00",
							"retry": 0,
							"retryIntervalInSeconds": 30,
							"secureOutput": false,
							"secureInput": false
						},
						"userProperties": [],
						"typeProperties": {
							"source": {
								"type": "JsonSource",
								"storeSettings": {
									"type": "HttpReadSettings",
									"requestMethod": "GET"
								},
								"formatSettings": {
									"type": "JsonReadSettings"
								}
							},
							"sink": {
								"type": "JsonSink",
								"storeSettings": {
									"type": "AzureBlobFSWriteSettings"
								},
								"formatSettings": {
									"type": "JsonWriteSettings"
								}
							},
							"enableStaging": false
						},
						"inputs": [
							{
								"referenceName": "ds_http_server",
								"type": "DatasetReference",
								"parameters": {
									"relative_url": "drivers.json?limit=1000"
								}
							}
						],
						"outputs": [
							{
								"referenceName": "ds_adls_storage",
								"type": "DatasetReference",
								"parameters": {
									"directory_path": {
										"value": "@concat('bronze/drivers/',string(utcnow('yyyyMMdd')))",
										"type": "Expression"
									},
									"filename": "drivers.json"
								}
							}
						]
					}
				],
				"policy": {
					"elapsedTimeMetric": {}
				},
				"folder": {
					"name": "ingestion"
				},
				"annotations": [],
				"lastPublishTime": "2024-04-12T18:05:40Z"
			},
			"dependsOn": []
		},
		{
			"name": "[concat(parameters('factoryName'), '/pl_season_round_child')]",
			"type": "Microsoft.DataFactory/factories/pipelines",
			"apiVersion": "2018-06-01",
			"properties": {
				"activities": [
					{
						"name": "Web1",
						"type": "WebActivity",
						"dependsOn": [],
						"policy": {
							"timeout": "0.12:00:00",
							"retry": 0,
							"retryIntervalInSeconds": 30,
							"secureOutput": false,
							"secureInput": false
						},
						"userProperties": [],
						"typeProperties": {
							"method": "GET",
							"headers": {},
							"url": {
								"value": "@concat('http://ergast.com/api/f1/',pipeline().parameters.take_season_from_parents,'.json')",
								"type": "Expression"
							}
						}
					},
					{
						"name": "ForEach1",
						"type": "ForEach",
						"dependsOn": [
							{
								"activity": "Web1",
								"dependencyConditions": [
									"Succeeded"
								]
							}
						],
						"userProperties": [],
						"typeProperties": {
							"items": {
								"value": "@activity('Web1').output.NRData.RaceTable.races",
								"type": "Expression"
							},
							"isSequential": true,
							"activities": [
								{
									"name": "Web2",
									"type": "WebActivity",
									"dependsOn": [],
									"policy": {
										"timeout": "0.12:00:00",
										"retry": 0,
										"retryIntervalInSeconds": 30,
										"secureOutput": false,
										"secureInput": false
									},
									"userProperties": [],
									"typeProperties": {
										"method": "GET",
										"headers": {},
										"url": {
											"value": "@concat('http://ergast.com/api/f1/',pipeline().parameters.take_season_from_parents,'/',item().round,'/','results.json?limit=100')",
											"type": "Expression"
										}
									}
								},
								{
									"name": "set_var_round_wise",
									"type": "SetVariable",
									"dependsOn": [
										{
											"activity": "Web2",
											"dependencyConditions": [
												"Succeeded"
											]
										}
									],
									"policy": {
										"secureOutput": false,
										"secureInput": false
									},
									"userProperties": [],
									"typeProperties": {
										"variableName": "round_wise_data",
										"value": {
											"value": "@{activity('Web2').output.MRData.RaceTable.Races}",
											"type": "Expression"
										}
									}
								},
								{
									"name": "act_copy_schedule_season",
									"type": "Copy",
									"dependsOn": [
										{
											"activity": "set_var_round_wise",
											"dependencyConditions": [
												"Succeeded"
											]
										}
									],
									"policy": {
										"timeout": "0.12:00:00",
										"retry": 0,
										"retryIntervalInSeconds": 30,
										"secureOutput": false,
										"secureInput": false
									},
									"userProperties": [],
									"typeProperties": {
										"source": {
											"type": "DelimitedTextSource",
											"additionalColumns": [
												{
													"name": "col",
													"value": {
														"value": "@variables('round_wise_data')",
														"type": "Expression"
													}
												}
											],
											"storeSettings": {
												"type": "AzureBlobFSReadSettings",
												"recursive": true,
												"enablePartitionDiscovery": false
											},
											"formatSettings": {
												"type": "DelimitedTextReadSettings"
											}
										},
										"sink": {
											"type": "DelimitedTextSink",
											"storeSettings": {
												"type": "AzureBlobFSWriteSettings"
											},
											"formatSettings": {
												"type": "DelimitedTextWriteSettings",
												"quoteAllText": true,
												"fileExtension": ".txt"
											}
										},
										"enableStaging": false,
										"translator": {
											"type": "TabularTranslator",
											"mappings": [
												{
													"source": {
														"name": "col",
														"type": "String"
													},
													"sink": {
														"type": "String",
														"physicalType": "String",
														"ordinal": 1
													}
												}
											],
											"typeConversion": true,
											"typeConversionSettings": {
												"allowDataTruncation": true,
												"treatBooleanAsNumber": false
											}
										}
									},
									"inputs": [
										{
											"referenceName": "ds_web_source_year",
											"type": "DatasetReference",
											"parameters": {}
										}
									],
									"outputs": [
										{
											"referenceName": "ds_sink_round_wise_data",
											"type": "DatasetReference",
											"parameters": {
												"file_name_round": {
													"value": "@item().round",
													"type": "Expression"
												},
												"file_name_year": {
													"value": "@pipeline().parameters.take_season_from_parents",
													"type": "Expression"
												}
											}
										}
									]
								}
							]
						}
					}
				],
				"policy": {
					"elapsedTimeMetric": {}
				},
				"parameters": {
					"take_season_from_parents": {
						"type": "string"
					}
				},
				"variables": {
					"take_year_from_parents": {
						"type": "String"
					},
					"round_wise_data": {
						"type": "String"
					}
				},
				"folder": {
					"name": "ingestion"
				},
				"annotations": [],
				"lastPublishTime": "2024-04-26T18:35:12Z"
			},
			"dependsOn": [
				"[concat(variables('factoryId'), '/datasets/ds_web_source_year')]"
			]
		},
		{
			"name": "[concat(parameters('factoryName'), '/pl_seasons_url')]",
			"type": "Microsoft.DataFactory/factories/pipelines",
			"apiVersion": "2018-06-01",
			"properties": {
				"activities": [
					{
						"name": "Web_url",
						"type": "WebActivity",
						"dependsOn": [],
						"policy": {
							"timeout": "0.12:00:00",
							"retry": 0,
							"retryIntervalInSeconds": 30,
							"secureOutput": false,
							"secureInput": false
						},
						"userProperties": [],
						"typeProperties": {
							"method": "GET",
							"headers": {},
							"url": "http://ergast.com/api/f1/seasons.json"
						}
					},
					{
						"name": "Set_variable_for_url",
						"type": "SetVariable",
						"dependsOn": [
							{
								"activity": "Web_url",
								"dependencyConditions": [
									"Succeeded"
								]
							}
						],
						"policy": {
							"secureOutput": false,
							"secureInput": false
						},
						"userProperties": [],
						"typeProperties": {
							"variableName": "year_wise_url",
							"value": {
								"value": "@{activity('Web_url').output}",
								"type": "Expression"
							}
						}
					},
					{
						"name": "copy_years",
						"type": "Copy",
						"dependsOn": [
							{
								"activity": "Set_variable_for_url",
								"dependencyConditions": [
									"Succeeded"
								]
							}
						],
						"policy": {
							"timeout": "0.12:00:00",
							"retry": 0,
							"retryIntervalInSeconds": 30,
							"secureOutput": false,
							"secureInput": false
						},
						"userProperties": [],
						"typeProperties": {
							"source": {
								"type": "DelimitedTextSource",
								"additionalColumns": [
									{
										"name": "col",
										"value": {
											"value": "@variables('year_wise_url')",
											"type": "Expression"
										}
									}
								],
								"storeSettings": {
									"type": "AzureBlobFSReadSettings",
									"recursive": true,
									"enablePartitionDiscovery": false
								},
								"formatSettings": {
									"type": "DelimitedTextReadSettings"
								}
							},
							"sink": {
								"type": "DelimitedTextSink",
								"storeSettings": {
									"type": "AzureBlobFSWriteSettings"
								},
								"formatSettings": {
									"type": "DelimitedTextWriteSettings",
									"quoteAllText": true,
									"fileExtension": ".txt"
								}
							},
							"enableStaging": false,
							"translator": {
								"type": "TabularTranslator",
								"mappings": [
									{
										"source": {
											"name": "col",
											"type": "String"
										},
										"sink": {
											"type": "String",
											"physicalType": "String",
											"ordinal": 1
										}
									}
								],
								"typeConversion": true,
								"typeConversionSettings": {
									"allowDataTruncation": true,
									"treatBooleanAsNumber": false
								}
							}
						},
						"inputs": [
							{
								"referenceName": "ds_web_source_year",
								"type": "DatasetReference",
								"parameters": {}
							}
						],
						"outputs": [
							{
								"referenceName": "ds_url_web",
								"type": "DatasetReference",
								"parameters": {
									"file_name": "seasons"
								}
							}
						]
					}
				],
				"policy": {
					"elapsedTimeMetric": {}
				},
				"variables": {
					"year_wise_url": {
						"type": "String"
					},
					"year": {
						"type": "String"
					},
					"take_year_from_parents": {
						"type": "String"
					},
					"round_wise_data": {
						"type": "String"
					}
				},
				"folder": {
					"name": "ingestion"
				},
				"annotations": [],
				"lastPublishTime": "2024-04-26T18:35:12Z"
			},
			"dependsOn": [
				"[concat(variables('factoryId'), '/datasets/ds_web_source_year')]",
				"[concat(variables('factoryId'), '/datasets/ds_url_web')]"
			]
		},
		{
			"name": "[concat(parameters('factoryName'), '/PL_INGEST_RACES_DATA')]",
			"type": "Microsoft.DataFactory/factories/pipelines",
			"apiVersion": "2018-06-01",
			"properties": {
				"activities": [
					{
						"name": "act_Web1",
						"type": "WebActivity",
						"dependsOn": [],
						"policy": {
							"timeout": "0.12:00:00",
							"retry": 0,
							"retryIntervalInSeconds": 30,
							"secureOutput": false,
							"secureInput": false
						},
						"userProperties": [],
						"typeProperties": {
							"method": "GET",
							"headers": {},
							"url": {
								"value": "http://ergast.com/api/f1/seasons.json",
								"type": "Expression"
							}
						}
					},
					{
						"name": "act_Set_seasons_limit_variable",
						"type": "SetVariable",
						"dependsOn": [
							{
								"activity": "act_Web1",
								"dependencyConditions": [
									"Succeeded"
								]
							}
						],
						"policy": {
							"secureOutput": false,
							"secureInput": false
						},
						"userProperties": [],
						"typeProperties": {
							"variableName": "seasons_limit",
							"value": {
								"value": "@activity('act_Web1').output.MRData.total",
								"type": "Expression"
							}
						}
					},
					{
						"name": "act_Web2",
						"type": "WebActivity",
						"dependsOn": [
							{
								"activity": "act_Set_seasons_limit_variable",
								"dependencyConditions": [
									"Succeeded"
								]
							}
						],
						"policy": {
							"timeout": "0.12:00:00",
							"retry": 0,
							"retryIntervalInSeconds": 30,
							"secureOutput": false,
							"secureInput": false
						},
						"userProperties": [],
						"typeProperties": {
							"method": "GET",
							"headers": {},
							"url": {
								"value": "@concat('http://ergast.com/api/f1/seasons.json?limit=',variables('seasons_limit'))",
								"type": "Expression"
							}
						}
					},
					{
						"name": "act_ForEach_season_iteration",
						"description": "This activity will iterate through each season",
						"type": "ForEach",
						"dependsOn": [
							{
								"activity": "act_Web2",
								"dependencyConditions": [
									"Succeeded"
								]
							}
						],
						"userProperties": [],
						"typeProperties": {
							"items": {
								"value": "@activity('act_Web2').output.MRData.SeasonTable.Seasons",
								"type": "Expression"
							},
							"isSequential": true,
							"activities": [
								{
									"name": "act_Set_season_value_variable",
									"description": "This activity will save season value in variable to pass this value in child pipeline",
									"type": "SetVariable",
									"dependsOn": [],
									"policy": {
										"secureOutput": false,
										"secureInput": false
									},
									"userProperties": [],
									"typeProperties": {
										"variableName": "year",
										"value": {
											"value": "@item().season",
											"type": "Expression"
										}
									}
								},
								{
									"name": "act_Execute_Race_Result_Pipeline",
									"description": "This activity will run Race Results pipeline as child pipeline",
									"type": "ExecutePipeline",
									"dependsOn": [
										{
											"activity": "act_Set_season_value_variable",
											"dependencyConditions": [
												"Succeeded"
											]
										}
									],
									"policy": {
										"secureInput": false
									},
									"userProperties": [],
									"typeProperties": {
										"pipeline": {
											"referenceName": "PL_INGEST_RESULTS_DATA",
											"type": "PipelineReference"
										},
										"waitOnCompletion": true,
										"parameters": {
											"year_from_races_pl": {
												"value": "@variables('year')",
												"type": "Expression"
											}
										}
									}
								},
								{
									"name": "act_Web3",
									"type": "WebActivity",
									"dependsOn": [
										{
											"activity": "act_Execute_Race_Result_Pipeline",
											"dependencyConditions": [
												"Succeeded"
											]
										}
									],
									"policy": {
										"timeout": "0.12:00:00",
										"retry": 0,
										"retryIntervalInSeconds": 30,
										"secureOutput": false,
										"secureInput": false
									},
									"userProperties": [],
									"typeProperties": {
										"method": "GET",
										"headers": {},
										"url": {
											"value": "@concat('http://ergast.com/api/f1/',item().season,'.json?limit=100')",
											"type": "Expression"
										}
									}
								},
								{
									"name": "act_Set_Races_data_variable",
									"description": "This activity will write races data season wise in variable",
									"type": "SetVariable",
									"dependsOn": [
										{
											"activity": "act_Web3",
											"dependencyConditions": [
												"Succeeded"
											]
										}
									],
									"policy": {
										"secureOutput": false,
										"secureInput": false
									},
									"userProperties": [],
									"typeProperties": {
										"variableName": "races_data",
										"value": {
											"value": "@{activity('act_Web3').output.MRData.RaceTable.Races}",
											"type": "Expression"
										}
									}
								},
								{
									"name": "act_Copy_races_data_to_ bronze",
									"description": "This activity will save Races data taken from API to bronze container in JSON file format",
									"type": "Copy",
									"dependsOn": [
										{
											"activity": "act_Set_Races_data_variable",
											"dependencyConditions": [
												"Succeeded"
											]
										}
									],
									"policy": {
										"timeout": "0.12:00:00",
										"retry": 0,
										"retryIntervalInSeconds": 30,
										"secureOutput": false,
										"secureInput": false
									},
									"userProperties": [],
									"typeProperties": {
										"source": {
											"type": "DelimitedTextSource",
											"additionalColumns": [
												{
													"name": "my_column",
													"value": {
														"value": "@variables('races_data')",
														"type": "Expression"
													}
												}
											],
											"storeSettings": {
												"type": "AzureBlobFSReadSettings",
												"recursive": true,
												"enablePartitionDiscovery": false
											},
											"formatSettings": {
												"type": "DelimitedTextReadSettings"
											}
										},
										"sink": {
											"type": "DelimitedTextSink",
											"storeSettings": {
												"type": "AzureBlobFSWriteSettings"
											},
											"formatSettings": {
												"type": "DelimitedTextWriteSettings",
												"quoteAllText": true,
												"fileExtension": ".txt"
											}
										},
										"enableStaging": false,
										"translator": {
											"type": "TabularTranslator",
											"mappings": [
												{
													"source": {
														"name": "my_column",
														"type": "String"
													},
													"sink": {
														"type": "String",
														"physicalType": "String",
														"ordinal": 1
													}
												}
											],
											"typeConversion": true,
											"typeConversionSettings": {
												"allowDataTruncation": true,
												"treatBooleanAsNumber": false
											}
										}
									},
									"inputs": [
										{
											"referenceName": "DS_SOURCE_TEMP_TXT_DATA5",
											"type": "DatasetReference",
											"parameters": {}
										}
									],
									"outputs": [
										{
											"referenceName": "DS_SINK_RACES_DATA1",
											"type": "DatasetReference",
											"parameters": {}
										}
									]
								}
							]
						}
					}
				],
				"policy": {
					"elapsedTimeMetric": {}
				},
				"variables": {
					"seasons_limit": {
						"type": "String"
					},
					"year": {
						"type": "String"
					},
					"races_data": {
						"type": "String"
					},
					"race_results_data": {
						"type": "String"
					}
				},
				"folder": {
					"name": "API_Ingestion_Pipelines"
				},
				"annotations": []
			},
			"dependsOn": [
				"[concat(variables('factoryId'), '/pipelines/PL_INGEST_RESULTS_DATA')]"
			]
		},
		{
			"name": "[concat(parameters('factoryName'), '/pl_seasons_years_parents')]",
			"type": "Microsoft.DataFactory/factories/pipelines",
			"apiVersion": "2018-06-01",
			"properties": {
				"activities": [
					{
						"name": "act_web",
						"type": "WebActivity",
						"dependsOn": [],
						"policy": {
							"timeout": "0.12:00:00",
							"retry": 0,
							"retryIntervalInSeconds": 30,
							"secureOutput": false,
							"secureInput": false
						},
						"userProperties": [],
						"typeProperties": {
							"method": "GET",
							"headers": {},
							"url": "http://ergast.com/api/f1/seasons.json?limit=100"
						}
					},
					{
						"name": "act_get_year",
						"type": "ForEach",
						"dependsOn": [
							{
								"activity": "act_web",
								"dependencyConditions": [
									"Succeeded"
								]
							}
						],
						"userProperties": [],
						"typeProperties": {
							"items": {
								"value": "@activity('act_web').output.MRData.SeasonTable.Seasons",
								"type": "Expression"
							},
							"isSequential": true,
							"activities": [
								{
									"name": "Web1",
									"type": "WebActivity",
									"dependsOn": [],
									"policy": {
										"timeout": "0.12:00:00",
										"retry": 0,
										"retryIntervalInSeconds": 30,
										"secureOutput": false,
										"secureInput": false
									},
									"userProperties": [],
									"typeProperties": {
										"method": "GET",
										"headers": {},
										"url": {
											"value": "@concat('http://ergast.com/api/f1/',item().season,'.json?limit=100') ",
											"type": "Expression"
										}
									}
								},
								{
									"name": "act_set_var1",
									"type": "SetVariable",
									"dependsOn": [
										{
											"activity": "Web1",
											"dependencyConditions": [
												"Succeeded"
											]
										}
									],
									"policy": {
										"secureOutput": false,
										"secureInput": false
									},
									"userProperties": [],
									"typeProperties": {
										"variableName": "year",
										"value": {
											"value": "@{activity('Web1').output.MRData.RaceTable.Races}",
											"type": "Expression"
										}
									}
								},
								{
									"name": "act_copy_schedule_seasons",
									"type": "Copy",
									"dependsOn": [
										{
											"activity": "act_set_var1",
											"dependencyConditions": [
												"Succeeded"
											]
										}
									],
									"policy": {
										"timeout": "0.12:00:00",
										"retry": 0,
										"retryIntervalInSeconds": 30,
										"secureOutput": false,
										"secureInput": false
									},
									"userProperties": [],
									"typeProperties": {
										"source": {
											"type": "DelimitedTextSource",
											"additionalColumns": [
												{
													"name": "col",
													"value": {
														"value": "@variables('year')",
														"type": "Expression"
													}
												}
											],
											"storeSettings": {
												"type": "AzureBlobFSReadSettings",
												"recursive": true,
												"enablePartitionDiscovery": false
											},
											"formatSettings": {
												"type": "DelimitedTextReadSettings"
											}
										},
										"sink": {
											"type": "DelimitedTextSink",
											"storeSettings": {
												"type": "AzureBlobFSWriteSettings"
											},
											"formatSettings": {
												"type": "DelimitedTextWriteSettings",
												"quoteAllText": true,
												"fileExtension": ".txt"
											}
										},
										"enableStaging": false,
										"translator": {
											"type": "TabularTranslator",
											"mappings": [
												{
													"source": {
														"name": "col",
														"type": "String"
													},
													"sink": {
														"type": "String",
														"physicalType": "String",
														"ordinal": 1
													}
												}
											],
											"typeConversion": true,
											"typeConversionSettings": {
												"allowDataTruncation": true,
												"treatBooleanAsNumber": false
											}
										}
									},
									"inputs": [
										{
											"referenceName": "ds_web_source_year",
											"type": "DatasetReference",
											"parameters": {}
										}
									],
									"outputs": [
										{
											"referenceName": "ds_year_parents",
											"type": "DatasetReference",
											"parameters": {}
										}
									]
								},
								{
									"name": "set_var_for_child",
									"type": "SetVariable",
									"dependsOn": [
										{
											"activity": "Web1",
											"dependencyConditions": [
												"Succeeded"
											]
										}
									],
									"policy": {
										"secureOutput": false,
										"secureInput": false
									},
									"userProperties": [],
									"typeProperties": {
										"variableName": "take_year_from_parents",
										"value": {
											"value": "@item().season",
											"type": "Expression"
										}
									}
								},
								{
									"name": "act_execute_child_pipeline",
									"type": "ExecutePipeline",
									"dependsOn": [
										{
											"activity": "set_var_for_child",
											"dependencyConditions": [
												"Succeeded"
											]
										}
									],
									"policy": {
										"secureInput": false
									},
									"userProperties": [],
									"typeProperties": {
										"pipeline": {
											"referenceName": "pl_season_round_child",
											"type": "PipelineReference"
										},
										"waitOnCompletion": true,
										"parameters": {
											"take_season_from_parents": {
												"value": "@variables('take_year_from_parents')",
												"type": "Expression"
											}
										}
									}
								}
							]
						}
					}
				],
				"policy": {
					"elapsedTimeMetric": {}
				},
				"variables": {
					"year": {
						"type": "String"
					},
					"take_year_from_parents": {
						"type": "String"
					},
					"round_wise_data": {
						"type": "String"
					}
				},
				"folder": {
					"name": "ingestion"
				},
				"annotations": [],
				"lastPublishTime": "2024-04-26T18:35:13Z"
			},
			"dependsOn": [
				"[concat(variables('factoryId'), '/datasets/ds_web_source_year')]",
				"[concat(variables('factoryId'), '/datasets/ds_year_parents')]",
				"[concat(variables('factoryId'), '/pipelines/pl_season_round_child')]"
			]
		}
	]
}